pyexml/__init__.py
pyexml/datasets/__init__.py
pyexml/datasets/_maps.py
pyexml/datasets/dynamic.py
pyexml/datasets/image_loader.py
pyexml/datasets/metricspace.py
pyexml/datasets/utils.py
pyexml/generators/__init__.py
pyexml/generators/latticegenerator.py
pyexml/geometry/__init__.py
pyexml/geometry/operator.py
pyexml/geometry/maps/__init__.py
pyexml/geometry/maps/_map.py
pyexml/geometry/maps/static.py
pyexml/geometry/maps/utils.py
pyexml/geometry/metrics/__init__.py
pyexml/geometry/metrics/metric.py
pyexml/geometry/metrics/numpy_metrics.py
pyexml/geometry/metrics/torch_metrics.py
pyexml/geometry/metrics/numpy/__init__.py
pyexml/geometry/metrics/numpy/outerproduct.py
pyexml/geometry/metrics/torch/__init__.py
pyexml/mlsubjects/__init__.py
pyexml/mlsubjects/dynamicnetsubject.py
pyexml/mlsubjects/metricnetsubject.py
pyexml/mlsubjects/neuralnetsubject.py
pyexml/models/__init__.py
pyexml/models/ffwd.py
pyexml/models/metricnet.py
pyexml/models/model.py
pyexml/plot/__init__.py
pyexml/plot/axis_plot.py
pyexml/plot/format.py
pyexml/trainers/__init__.py
pyexml/trainers/coach.py
pyexml/trainers/trainer.py
pyexml/trainers/trainer_schedule.py
pyexml-0.0.1.dist-info/LICENSE
pyexml-0.0.1.dist-info/METADATA
pyexml-0.0.1.dist-info/WHEEL
pyexml-0.0.1.dist-info/top_level.txt
pyexml-0.0.1.dist-info/RECORD
